imagesmacker/__init__.py
imagesmacker/draw.py
imagesmacker/exceptions.py
imagesmacker/fields.py
imagesmacker/fonts.py
imagesmacker/image.py
imagesmacker/utils.py
imagesmacker/models/__init__.py
imagesmacker/models/coordinates.py
imagesmacker/models/draw.py
imagesmacker/models/fields.py
imagesmacker-5.0.0.dist-info/METADATA
imagesmacker-5.0.0.dist-info/WHEEL
imagesmacker-5.0.0.dist-info/top_level.txt
imagesmacker-5.0.0.dist-info/RECORD
